gh_space_shooter/__init__.py
gh_space_shooter/cli.py
gh_space_shooter/console_printer.py
gh_space_shooter/constants.py
gh_space_shooter/github_client.py
gh_space_shooter/py.typed
gh_space_shooter/game/__init__.py
gh_space_shooter/game/animator.py
gh_space_shooter/game/game_state.py
gh_space_shooter/game/render_context.py
gh_space_shooter/game/renderer.py
gh_space_shooter/game/drawables/__init__.py
gh_space_shooter/game/drawables/bullet.py
gh_space_shooter/game/drawables/drawable.py
gh_space_shooter/game/drawables/enemy.py
gh_space_shooter/game/drawables/explosion.py
gh_space_shooter/game/drawables/ship.py
gh_space_shooter/game/drawables/starfield.py
gh_space_shooter/game/strategies/__init__.py
gh_space_shooter/game/strategies/base_strategy.py
gh_space_shooter/game/strategies/column_strategy.py
gh_space_shooter/game/strategies/random_strategy.py
gh_space_shooter/game/strategies/row_strategy.py
gh_space_shooter-0.0.5.dist-info/METADATA
gh_space_shooter-0.0.5.dist-info/WHEEL
gh_space_shooter-0.0.5.dist-info/entry_points.txt
gh_space_shooter-0.0.5.dist-info/licenses/LICENSE
gh_space_shooter-0.0.5.dist-info/RECORD
