Metadata-Version: 2.4
Name: gh-space-shooter
Version: 0.0.5
Summary: A CLI tool that visualizes GitHub contribution graphs as gamified GIFs
Author-email: zane <czl970721@gmail.com>
License-File: LICENSE
Requires-Python: >=3.13
Requires-Dist: httpx>=0.27.0
Requires-Dist: pillow>=10.1.0
Requires-Dist: python-dotenv>=1.0.0
Requires-Dist: rich>=13.0.0
Requires-Dist: typer>=0.12.0
Provides-Extra: dev
Requires-Dist: pytest>=8.0.0; extra == 'dev'
